dschmidt_cdktf_provider_google_beta/__init__.py
dschmidt_cdktf_provider_google_beta/py.typed
dschmidt_cdktf_provider_google_beta/_jsii/__init__.py
dschmidt_cdktf_provider_google_beta/_jsii/provider-google-beta@0.1.0.jsii.tgz
dschmidt_cdktf_provider_google_beta/data_google_access_approval_folder_service_account/__init__.py
dschmidt_cdktf_provider_google_beta/data_google_access_approval_organization_service_account/__init__.py
dschmidt_cdktf_provider_google_beta/data_google_access_approval_project_service_account/__init__.py
dschmidt_cdktf_provider_google_beta/data_google_active_folder/__init__.py
dschmidt_cdktf_provider_google_beta/data_google_app_engine_default_service_account/__init__.py
dschmidt_cdktf_provider_google_beta/data_google_bigquery_default_service_account/__init__.py
dschmidt_cdktf_provider_google_beta/data_google_billing_account/__init__.py
dschmidt_cdktf_provider_google_beta/data_google_client_config/__init__.py
dschmidt_cdktf_provider_google_beta/data_google_client_openid_userinfo/__init__.py
dschmidt_cdktf_provider_google_beta/data_google_cloud_identity_group_memberships/__init__.py
dschmidt_cdktf_provider_google_beta/data_google_cloud_identity_groups/__init__.py
dschmidt_cdktf_provider_google_beta/data_google_cloud_run_locations/__init__.py
dschmidt_cdktf_provider_google_beta/data_google_cloud_run_service/__init__.py
dschmidt_cdktf_provider_google_beta/data_google_cloudfunctions_function/__init__.py
dschmidt_cdktf_provider_google_beta/data_google_composer_environment/__init__.py
dschmidt_cdktf_provider_google_beta/data_google_composer_image_versions/__init__.py
dschmidt_cdktf_provider_google_beta/data_google_compute_address/__init__.py
dschmidt_cdktf_provider_google_beta/data_google_compute_backend_bucket/__init__.py
dschmidt_cdktf_provider_google_beta/data_google_compute_backend_service/__init__.py
dschmidt_cdktf_provider_google_beta/data_google_compute_default_service_account/__init__.py
dschmidt_cdktf_provider_google_beta-0.1.0.dist-info/LICENSE
dschmidt_cdktf_provider_google_beta-0.1.0.dist-info/METADATA
dschmidt_cdktf_provider_google_beta-0.1.0.dist-info/WHEEL
dschmidt_cdktf_provider_google_beta-0.1.0.dist-info/top_level.txt
dschmidt_cdktf_provider_google_beta-0.1.0.dist-info/RECORD
